[
		{
			"Category": "Animals & Pets",
			"Keywords": ["Cats", "Dogs", "Penguins"]
		},
		{
			"Category": "Autos & Vehicles",
			"Keywords": []
		},
		{
			"Category": "Education",
			"Keywords": []
		},
		{
			"Category": "Entertainment",
			"Keywords": []
		},
		{
			"Category": "Fashion & Style",
			"Keywords": []
		},
		{
			"Category": "Gaming",
			"Keywords": []
		},
		{
			"Category": "Music",
			"Keywords": []
		},
		{
			"Category": "News & Politics",
			"Keywords": []
		},
		{
			"Category": "People",
			"Keywords": []
		},
		{
			"Category": "Science & Technology",
			"Keywords": []
		},
		{
			"Category": "Sports",
			"Keywords": ["Baseball", "Basketball", "Football", "Golf", "Hockey", "Soccer", "Swimming"]
		},
		{
			"Category": "Travel",
			"Keywords": []
		}
		
]